ecocash/__init__.py
ecocash-0.0.6.dist-info/METADATA
ecocash-0.0.6.dist-info/WHEEL
ecocash-0.0.6.dist-info/top_level.txt
ecocash-0.0.6.dist-info/RECORD
