Metadata-Version: 2.4
Name: ecocash
Version: 0.0.6
Summary: Unofficial Python Wrapper Library for the EcoCash API by Tarmica Sean Chiwara, A computer engineering student.
Author-email: Tarmica Sean Chiwara <tarimicac@gmail.com>
Project-URL: Homepage, https://github.com/lordskyzw/ecocash
Classifier: Programming Language :: Python :: 3
Classifier: License :: OSI Approved :: MIT License
Classifier: Operating System :: OS Independent
Requires-Python: >=3.8
